Metadata-Version: 2.1
Name: odoo14-addon-l10n-es-mis-report
Version: 14.0.1.4.0
Summary: Plantillas MIS Builder para informes contables españoles
Home-page: https://github.com/OCA/l10n-spain
Author: ForgeFlow, Tecnativa, Odoo Community Association (OCA)
Author-email: support@odoo-community.org
License: AGPL-3
Platform: UNKNOWN
Classifier: Programming Language :: Python
Classifier: Framework :: Odoo
Classifier: Framework :: Odoo :: 14.0
Classifier: License :: OSI Approved :: GNU Affero General Public License v3
Requires-Python: >=3.6
Requires-Dist: odoo14-addon-mis-builder
Requires-Dist: odoo <14.1dev,>=14.0a
